pre_commit_download/__init__.py
pre_commit_download/_backend.py
pre_commit_download/hooks.py
pre_commit_download/py.typed
pre_commit_download-0.1.0.dist-info/LICENSE
pre_commit_download-0.1.0.dist-info/METADATA
pre_commit_download-0.1.0.dist-info/WHEEL
pre_commit_download-0.1.0.dist-info/top_level.txt
pre_commit_download-0.1.0.dist-info/RECORD
