Metadata-Version: 2.1
Name: pre-commit-download
Version: 0.1.0
Summary: Build-backend for downloading external single file binaries.
Author-email: Pavel Kolomytsev <pkolomytsev@gmail.com>
Project-URL: Homepage, https://github.com/pkolomytsev/pre-commit-download
Classifier: Development Status :: 3 - Alpha
Classifier: Environment :: Console
Classifier: Intended Audience :: Developers
Classifier: License :: OSI Approved :: MIT License
Classifier: Operating System :: OS Independent
Classifier: Natural Language :: English
Classifier: Programming Language :: Python :: 3.8
Classifier: Topic :: Software Development
Classifier: Typing :: Typed
Requires-Python: >=3.8
License-File: LICENSE
Requires-Dist: setuptools ~=69.0
Requires-Dist: tomli ~=2.0
Provides-Extra: dev
Requires-Dist: pre-commit ==3.5.0 ; extra == 'dev'
Requires-Dist: nox ==2024.4.15 ; extra == 'dev'
Requires-Dist: build ==1.2.1 ; extra == 'dev'
Requires-Dist: twine ==5.0.0 ; extra == 'dev'
Requires-Dist: pre-commit-download[lint] ; extra == 'dev'
Requires-Dist: pre-commit-download[test] ; extra == 'dev'
Provides-Extra: lint
Requires-Dist: Flake8-pyproject ==1.2.3 ; extra == 'lint'
Requires-Dist: wemake-python-styleguide ==0.18.0 ; extra == 'lint'
Requires-Dist: mypy ==1.10.0 ; extra == 'lint'
Requires-Dist: black ==24.4.2 ; extra == 'lint'
Provides-Extra: test
Requires-Dist: pytest ==8.2.0 ; extra == 'test'
